README.md
setup.py
matchzoo/__init__.py
matchzoo/dataloader.py
matchzoo/embedding.py
matchzoo/logger.py
matchzoo/version.py
matchzoo/auto/__init__.py
matchzoo/auto/prepare.py
matchzoo/auto/tuner.py
matchzoo/contrib/__init__.py
matchzoo/contrib/layers/__init__.py
matchzoo/contrib/models/__init__.py
matchzoo/contrib/models/match_lstm.py
matchzoo/data_generator/__init__.py
matchzoo/data_generator/data_generator.py
matchzoo/data_generator/dpool_data_generator.py
matchzoo/data_generator/dynamic_data_generator.py
matchzoo/data_generator/histogram_data_generator.py
matchzoo/data_generator/pair_data_generator.py
matchzoo/data_pack/__init__.py
matchzoo/data_pack/build_unit_from_data_pack.py
matchzoo/data_pack/build_vocab_unit.py
matchzoo/data_pack/data_pack.py
matchzoo/data_pack/pack.py
matchzoo/engine/__init__.py
matchzoo/engine/base_metric.py
matchzoo/engine/base_model.py
matchzoo/engine/base_preprocessor.py
matchzoo/engine/base_task.py
matchzoo/engine/callbacks.py
matchzoo/engine/hyper_spaces.py
matchzoo/engine/param.py
matchzoo/engine/param_table.py
matchzoo/layers/__init__.py
matchzoo/layers/dynamic_pooling_layer.py
matchzoo/layers/matching_layer.py
matchzoo/losses/__init__.py
matchzoo/losses/rank_cross_entropy_loss.py
matchzoo/losses/rank_hinge_loss.py
matchzoo/metrics/__init__.py
matchzoo/metrics/average_precision.py
matchzoo/metrics/discounted_cumulative_gain.py
matchzoo/metrics/mean_average_precision.py
matchzoo/metrics/mean_reciprocal_rank.py
matchzoo/metrics/normalized_discounted_cumulative_gain.py
matchzoo/metrics/precision.py
matchzoo/models/__init__.py
matchzoo/models/arci.py
matchzoo/models/arcii.py
matchzoo/models/cdssm.py
matchzoo/models/conv_highway.py
matchzoo/models/dssm.py
matchzoo/models/duet.py
matchzoo/models/match_pyramid.py
matchzoo/models/mvlstm.py
matchzoo/models/parameter_readme_generator.py
matchzoo/preprocessors/__init__.py
matchzoo/preprocessors/basic_preprocessor.py
matchzoo/preprocessors/cdssm_preprocessor.py
matchzoo_lite.egg-info/PKG-INFO
matchzoo_lite.egg-info/SOURCES.txt
matchzoo_lite.egg-info/dependency_links.txt
matchzoo_lite.egg-info/requires.txt
matchzoo_lite.egg-info/top_level.txt