Metadata-Version: 2.1
Name: matchzoo-lite
Version: 0.1.4
Summary: Facilitating the design, comparison and sharing of deep text matching models. Based on MatchZoo
Home-page: https://github.com/4AI/matchzoo-lite
Author: Sean Lee
Author-email: xmlee@gmail.com
License: Apache 2.0
Keywords: text matching models based on https://github.com/NTMC-Community/MatchZoo
Platform: UNKNOWN
Classifier: Development Status :: 3 - Alpha
Classifier: Environment :: Console
Classifier: Operating System :: POSIX :: Linux
Classifier: Topic :: Scientific/Engineering :: Artificial Intelligence
Classifier: License :: OSI Approved :: Apache Software License
Classifier: Programming Language :: Python :: 3.6
Provides-Extra: tests
